Metadata-Version: 2.1
Name: bitfex
Version: 1.0.1
Summary: BitFex.Trade python API wrapper
Home-page: https://github.com/bitfex/bitfex_api.py
Author: BitFex.Trade
Author-email: support@bitfex.trade
License: UNKNOWN
Platform: UNKNOWN
Classifier: Programming Language :: Python :: 3
Classifier: License :: OSI Approved :: MIT License
Classifier: Operating System :: OS Independent
